cyglass/__init__.py
cyglass/f2c/__init__.py
cyglass/f2c/__main__.py
f2c-0.1.dist-info/DESCRIPTION.rst
f2c-0.1.dist-info/METADATA
f2c-0.1.dist-info/RECORD
f2c-0.1.dist-info/WHEEL
f2c-0.1.dist-info/entry_points.txt
f2c-0.1.dist-info/metadata.json
f2c-0.1.dist-info/top_level.txt
