Metadata-Version: 2.0
Name: f2c
Version: 0.1
Summary: Configuration utility for CyGlass Fortigate Integration
Home-page: https://github.com/CyGlass/fortinet-cyglass
Author: Josh Bregman
Author-email: josh.bregman@cyglass.com
License: UNKNOWN
Keywords: fortigate,cyglass,network
Platform: UNKNOWN
Requires-Dist: FortigateApi
